gspeak/__init__.py
gspeak/wrapper.py
gspeak-1.0.0.dist-info/LICENSE
gspeak-1.0.0.dist-info/METADATA
gspeak-1.0.0.dist-info/WHEEL
gspeak-1.0.0.dist-info/top_level.txt
gspeak-1.0.0.dist-info/RECORD
