Metadata-Version: 2.1
Name: gspeak
Version: 1.0.0
Summary: Simple wrapper for gTTS and pygame to play audio directly from buffer
Home-page: https://github.com/rcox771/gspeak
Author: rcox771
Author-email: 
License: MIT
Platform: UNKNOWN
Classifier: License :: OSI Approved :: MIT License
Classifier: Programming Language :: Python :: 3
Classifier: Programming Language :: Python :: 3.8
Requires-Dist: gTTS
Requires-Dist: pygame
